up2s3.py
up2s3-0.1.0.dist-info/LICENSE
up2s3-0.1.0.dist-info/METADATA
up2s3-0.1.0.dist-info/WHEEL
up2s3-0.1.0.dist-info/top_level.txt
up2s3-0.1.0.dist-info/RECORD
