Metadata-Version: 2.1
Name: up2s3
Version: 0.1.0
Summary: Save uploaded pictures in AWS S3.
Home-page: https://github.com/sapicd/up2s3
Author: staugur
Author-email: me@tcw.im
License: Apache 2.0
Platform: UNKNOWN
License-File: LICENSE
Requires-Dist: boto3
